setup.py
paraer/__init__.py
paraer/datastrctures.py
paraer/doc.py
paraer/fields.py
paraer/para.py
paraer/utils.py
paraer.egg-info/PKG-INFO
paraer.egg-info/SOURCES.txt
paraer.egg-info/dependency_links.txt
paraer.egg-info/not-zip-safe
paraer.egg-info/requires.txt
paraer.egg-info/top_level.txt